Metadata-Version: 2.1
Name: wp-connector
Version: 0.0.1
Summary: WorldPop Connector to get country border data
Home-page: https://github.com/Repsay/wp-connector
Author: Jasper Delahaije
Author-email: jdelahaije@gmail.com
License: MIT
Download-URL: https://github.com/Repsay/wp-connector/releases
Platform: UNKNOWN
Classifier: Development Status :: 2 - Pre-Alpha
Classifier: Intended Audience :: Developers
Classifier: Topic :: Software Development :: Libraries :: Python Modules
Classifier: Topic :: Utilities
Classifier: License :: OSI Approved :: MIT License
Classifier: Programming Language :: Python :: 3.8
Classifier: Programming Language :: Python :: 3.9
Classifier: Programming Language :: Python :: 3.10
Classifier: Natural Language :: English
Requires-Python: >=3.8
